enos/__init__.py
enos/input_control.py
myinputlib/__init__.py
myinputlib/input_control.py
pyenospy-1.0.0.dist-info/METADATA
pyenospy-1.0.0.dist-info/WHEEL
pyenospy-1.0.0.dist-info/top_level.txt
pyenospy-1.0.0.dist-info/RECORD
