Metadata-Version: 2.4
Name: pyenospy
Version: 1.0.0
Summary: Basit ve kullanışlı bir mouse ve klavye kontrol kütüphanesi
Home-page: https://github.com/yourusername/pyenospy
Author: enos
Author-email: enos@enos.com
Classifier: Programming Language :: Python :: 3
Classifier: License :: OSI Approved :: MIT License
Classifier: Operating System :: Microsoft :: Windows
Requires-Python: >=3.6
Requires-Dist: pywin32>=306
Dynamic: author
Dynamic: author-email
Dynamic: classifier
Dynamic: description
Dynamic: description-content-type
Dynamic: home-page
Dynamic: requires-dist
Dynamic: requires-python
Dynamic: summary
